notecoin/__init__.py
notecoin/base/__init__.py
notecoin/base/db/__init__.py
notecoin/base/db/mysql.py
notecoin/base/drive/__init__.py
notecoin/base/drive/job.py
notecoin/base/drive/lanzou.py
notecoin/base/drive/notecoin.db
notecoin/base/drive/oss.py
notecoin/base/drive/transform.py
notecoin/base/tables/__init__.py
notecoin/base/tables/kline.py
notecoin/base/tables/strategy.py
notecoin/base/tables/trade.py
notecoin/coins/__init__.py
notecoin/coins/base/__init__.py
notecoin/coins/base/file.py
notecoin/coins/base/load.py
notecoin/coins/okex/__init__.py
notecoin/coins/okex/load.py
notecoin/server/__init__.py
notecoin/server/download.py
notecoin/server/notecoin_celery.py
notecoin/server/notecoin_server.py
notecoin/server/script.py
notecoin/server/strategy.py
notecoin/server/connect/__init__.py
notecoin/server/connect/base.py
notecoin/strategy/__init__.py
notecoin/strategy/binance/__init__.py
notecoin/strategy/binance/auto.py
notecoin/strategy/binance/example2.py
notecoin/strategy/binance/strategy1.py
notecoin/strategy/binance/strategy2.py
notecoin/task/__init__.py
notecoin/task/base.py
notecoin/task/load.py
notecoin/utils/__init__.py
notecoin/utils/log.py
notecoin/utils/time.py
notecoin-0.26.19.dist-info/LICENSE
notecoin-0.26.19.dist-info/METADATA
notecoin-0.26.19.dist-info/WHEEL
notecoin-0.26.19.dist-info/entry_points.txt
notecoin-0.26.19.dist-info/top_level.txt
notecoin-0.26.19.dist-info/RECORD
