Metadata-Version: 2.1
Name: notecoin
Version: 0.26.19
Summary: notecoin
Home-page: https://github.com/1007530194
Author: niult
Author-email: 1007530194@qq.com
License-File: LICENSE
Requires-Dist: tqdm
Requires-Dist: xgboost
Requires-Dist: supervisor
Requires-Dist: notebuild
Requires-Dist: notefile
